abi3info/__init__.py
abi3info/_internal.py
abi3info/models.py
abi3info-2025.11.18.dist-info/licenses/LICENSE
abi3info-2025.11.18.dist-info/WHEEL
abi3info-2025.11.18.dist-info/METADATA
abi3info-2025.11.18.dist-info/RECORD
