Metadata-Version: 2.4
Name: abi3info
Version: 2025.11.18
Summary: A library for abi3 and other CPython API information
Author-email: William Woodruff <william@yossarian.net>
Requires-Python: >=3.10
License-Expression: MIT
Classifier: Programming Language :: Python :: 3 :: Only
Classifier: Programming Language :: Python :: 3
Classifier: Development Status :: 5 - Production/Stable
Classifier: Intended Audience :: Developers
Classifier: Topic :: Security
License-File: LICENSE
Project-URL: Documentation, https://woodruffw.github.io/abi3info/
Project-URL: Homepage, https://pypi.org/project/abi3info/
Project-URL: Issues, https://github.com/woodruffw/abi3info/issues
Project-URL: Source, https://github.com/woodruffw/abi3info
